__init__.py
pyMPSG/__init__.py
pyMPSG/depthmapper.py
pyMPSG/helper.py
pyMPSG/pointscanner.py
pyMPSG/setup.py
pyMPSG/streamfile.py
pyMPSG/streamgenerator.py
pympsg-1.0.2.dist-info/licenses/LICENSE
pympsg-1.0.2.dist-info/METADATA
pympsg-1.0.2.dist-info/WHEEL
pympsg-1.0.2.dist-info/top_level.txt
pympsg-1.0.2.dist-info/RECORD
