Metadata-Version: 2.4
Name: pyMPSG
Version: 1.0.2
Summary: Generate micropatterning streamfiles, e.g. for FEI HELIOS machines.
Author-email: René Vollmer <pyMPSG@aypac.de>
License-Expression: Apache-2.0
Project-URL: Homepage, https://github.com/Aypac/pyMPSG
Project-URL: Issues, https://github.com/Aypac/pyMPSG/issues
Project-URL: DOI, https://doi.org/10.5281/zenodo.17148127
Keywords: FEI,STRFILE,STREAMFILE,FIB,DUALBEAM,MILLING
Classifier: Programming Language :: Python :: 3
Classifier: Programming Language :: Python :: 3 :: Only
Classifier: Operating System :: OS Independent
Requires-Python: >=3.12
License-File: LICENSE
Requires-Dist: numpy>=2.2.4
Requires-Dist: matplotlib>=3.10.1
Requires-Dist: tabulate>=0.9.0
Dynamic: license-file
